{
"type": "FeatureCollection",
"name": "gare_in",
"crs": { "type": "name", "properties": { "name": "urn:ogc:def:crs:OGC:1.3:CRS84" } },
"features": [
{ "type": "Feature", "properties": { "fid": 13, "CODE_UIC": "87476002", "LIBELLE": "Lorient" }, "geometry": { "type": "Point", "coordinates": [ -3.366289623776526, 47.75512114124836 ] } },
{ "type": "Feature", "properties": { "fid": 16, "CODE_UIC": "87334508", "LIBELLE": "La Poterie" }, "geometry": { "type": "Point", "coordinates": [ -1.630584094846585, 48.091987661489782 ] } },
{ "type": "Feature", "properties": { "fid": 26, "CODE_UIC": "87478107", "LIBELLE": "St-Malo" }, "geometry": { "type": "Point", "coordinates": [ -2.004051313466777, 48.646530297329598 ] } },
{ "type": "Feature", "properties": { "fid": 28, "CODE_UIC": "87474007", "LIBELLE": "Brest" }, "geometry": { "type": "Point", "coordinates": [ -4.479243011743669, 48.387929795241199 ] } },
{ "type": "Feature", "properties": { "fid": 44, "CODE_UIC": "87473223", "LIBELLE": "Lannion" }, "geometry": { "type": "Point", "coordinates": [ -3.460362272489274, 48.727226158586063 ] } },
{ "type": "Feature", "properties": { "fid": 62, "CODE_UIC": "87478164", "LIBELLE": "Dinan" }, "geometry": { "type": "Point", "coordinates": [ -2.053387664537875, 48.45702207710471 ] } },
{ "type": "Feature", "properties": { "fid": 64, "CODE_UIC": "87471078", "LIBELLE": "Montfort-sur-Meu" }, "geometry": { "type": "Point", "coordinates": [ -1.948812414663325, 48.139089250337364 ] } },
{ "type": "Feature", "properties": { "fid": 78, "CODE_UIC": "87471508", "LIBELLE": "Vitré" }, "geometry": { "type": "Point", "coordinates": [ -1.212365535123974, 48.122529335131929 ] } },
{ "type": "Feature", "properties": { "fid": 97, "CODE_UIC": "87473504", "LIBELLE": "Carhaix" }, "geometry": { "type": "Point", "coordinates": [ -3.563916929202896, 48.276459740778542 ] } },
{ "type": "Feature", "properties": { "fid": 102, "CODE_UIC": "87474239", "LIBELLE": "Landerneau" }, "geometry": { "type": "Point", "coordinates": [ -4.256576427625531, 48.453747151173239 ] } },
{ "type": "Feature", "properties": { "fid": 136, "CODE_UIC": "87473009", "LIBELLE": "St-Brieuc" }, "geometry": { "type": "Point", "coordinates": [ -2.764962751496382, 48.507190983357148 ] } },
{ "type": "Feature", "properties": { "fid": 138, "CODE_UIC": "87471045", "LIBELLE": "Betton" }, "geometry": { "type": "Point", "coordinates": [ -1.634223144594651, 48.181400267622394 ] } },
{ "type": "Feature", "properties": { "fid": 147, "CODE_UIC": "87474098", "LIBELLE": "Quimper" }, "geometry": { "type": "Point", "coordinates": [ -4.092232861763613, 47.994823741411302 ] } },
{ "type": "Feature", "properties": { "fid": 166, "CODE_UIC": "87476606", "LIBELLE": "Vannes" }, "geometry": { "type": "Point", "coordinates": [ -2.752403881216251, 47.66520979265519 ] } },
{ "type": "Feature", "properties": { "fid": 175, "CODE_UIC": "87471391", "LIBELLE": "Pontchaillou" }, "geometry": { "type": "Point", "coordinates": [ -1.691801073204263, 48.118263556361427 ] } },
{ "type": "Feature", "properties": { "fid": 179, "CODE_UIC": "87471003", "LIBELLE": "Rennes" }, "geometry": { "type": "Point", "coordinates": [ -1.672881285302788, 48.103115825786759 ] } },
{ "type": "Feature", "properties": { "fid": 185, "CODE_UIC": "87471029", "LIBELLE": "Vern" }, "geometry": { "type": "Point", "coordinates": [ -1.596590935217561, 48.046974665413458 ] } }
]
}
